[{"area":"NO1","mean_price":1,"compensation":0,"type":"pos_comp","estimation_date":"2023-07-25","computation_year":2023,"computation_month":7},{"area":"NO1","mean_price":0.4682,"compensation":0,"type":"mean","estimation_date":"2023-07-25","computation_year":2023,"computation_month":7},{"area":"NO1","mean_price":0.46,"compensation":0,"type":"median","estimation_date":"2023-07-25","computation_year":2023,"computation_month":7},{"area":"NO1","mean_price":0.4001,"compensation":0,"type":"quantile_0.005","estimation_date":"2023-07-25","computation_year":2023,"computation_month":7},{"area":"NO1","mean_price":0.4001,"compensation":0,"type":"quantile_0.025","estimation_date":"2023-07-25","computation_year":2023,"computation_month":7},{"area":"NO1","mean_price":0.4034,"compensation":0,"type":"quantile_0.05","estimation_date":"2023-07-25","computation_year":2023,"computation_month":7},{"area":"NO1","mean_price":0.4102,"compensation":0,"type":"quantile_0.1","estimation_date":"2023-07-25","computation_year":2023,"computation_month":7},{"area":"NO1","mean_price":0.4279,"compensation":0,"type":"quantile_0.25","estimation_date":"2023-07-25","computation_year":2023,"computation_month":7},{"area":"NO1","mean_price":0.4996,"compensation":0,"type":"quantile_0.75","estimation_date":"2023-07-25","computation_year":2023,"computation_month":7},{"area":"NO1","mean_price":0.5384,"compensation":0,"type":"quantile_0.9","estimation_date":"2023-07-25","computation_year":2023,"computation_month":7},{"area":"NO1","mean_price":0.5609,"compensation":0,"type":"quantile_0.95","estimation_date":"2023-07-25","computation_year":2023,"computation_month":7},{"area":"NO1","mean_price":0.5808,"compensation":0,"type":"quantile_0.975","estimation_date":"2023-07-25","computation_year":2023,"computation_month":7},{"area":"NO1","mean_price":0.6153,"compensation":0,"type":"quantile_0.995","estimation_date":"2023-07-25","computation_year":2023,"computation_month":7},{"area":"NO1","mean_price":0.4001,"compensation":0,"type":"lower_bound","estimation_date":"2023-07-25","computation_year":2023,"computation_month":7},{"area":"NO1","mean_price":0.477,"compensation":0,"type":"current_mean","estimation_date":"2023-07-25","computation_year":2023,"computation_month":7},{"area":"NO2","mean_price":1,"compensation":0.3742,"type":"pos_comp","estimation_date":"2023-07-25","computation_year":2023,"computation_month":7},{"area":"NO2","mean_price":0.8559,"compensation":0.0161,"type":"mean","estimation_date":"2023-07-25","computation_year":2023,"computation_month":7},{"area":"NO2","mean_price":0.853,"compensation":0,"type":"median","estimation_date":"2023-07-25","computation_year":2023,"computation_month":7},{"area":"NO2","mean_price":0.726,"compensation":0,"type":"quantile_0.005","estimation_date":"2023-07-25","computation_year":2023,"computation_month":7},{"area":"NO2","mean_price":0.7445,"compensation":0,"type":"quantile_0.025","estimation_date":"2023-07-25","computation_year":2023,"computation_month":7},{"area":"NO2","mean_price":0.7573,"compensation":0,"type":"quantile_0.05","estimation_date":"2023-07-25","computation_year":2023,"computation_month":7},{"area":"NO2","mean_price":0.7738,"compensation":0,"type":"quantile_0.1","estimation_date":"2023-07-25","computation_year":2023,"computation_month":7},{"area":"NO2","mean_price":0.8083,"compensation":0,"type":"quantile_0.25","estimation_date":"2023-07-25","computation_year":2023,"computation_month":7},{"area":"NO2","mean_price":0.8997,"compensation":0.0222,"type":"quantile_0.75","estimation_date":"2023-07-25","computation_year":2023,"computation_month":7},{"area":"NO2","mean_price":0.9425,"compensation":0.0608,"type":"quantile_0.9","estimation_date":"2023-07-25","computation_year":2023,"computation_month":7},{"area":"NO2","mean_price":0.9659,"compensation":0.0818,"type":"quantile_0.95","estimation_date":"2023-07-25","computation_year":2023,"computation_month":7},{"area":"NO2","mean_price":0.9863,"compensation":0.1002,"type":"quantile_0.975","estimation_date":"2023-07-25","computation_year":2023,"computation_month":7},{"area":"NO2","mean_price":1.0225,"compensation":0.1328,"type":"quantile_0.995","estimation_date":"2023-07-25","computation_year":2023,"computation_month":7},{"area":"NO2","mean_price":0.7151,"compensation":0,"type":"lower_bound","estimation_date":"2023-07-25","computation_year":2023,"computation_month":7},{"area":"NO2","mean_price":0.8526,"compensation":0,"type":"current_mean","estimation_date":"2023-07-25","computation_year":2023,"computation_month":7},{"area":"NO3","mean_price":1,"compensation":0,"type":"pos_comp","estimation_date":"2023-07-25","computation_year":2023,"computation_month":7},{"area":"NO3","mean_price":0.3584,"compensation":0,"type":"mean","estimation_date":"2023-07-25","computation_year":2023,"computation_month":7},{"area":"NO3","mean_price":0.3539,"compensation":0,"type":"median","estimation_date":"2023-07-25","computation_year":2023,"computation_month":7},{"area":"NO3","mean_price":0.2969,"compensation":0,"type":"quantile_0.005","estimation_date":"2023-07-25","computation_year":2023,"computation_month":7},{"area":"NO3","mean_price":0.2988,"compensation":0,"type":"quantile_0.025","estimation_date":"2023-07-25","computation_year":2023,"computation_month":7},{"area":"NO3","mean_price":0.3021,"compensation":0,"type":"quantile_0.05","estimation_date":"2023-07-25","computation_year":2023,"computation_month":7},{"area":"NO3","mean_price":0.3076,"compensation":0,"type":"quantile_0.1","estimation_date":"2023-07-25","computation_year":2023,"computation_month":7},{"area":"NO3","mean_price":0.3248,"compensation":0,"type":"quantile_0.25","estimation_date":"2023-07-25","computation_year":2023,"computation_month":7},{"area":"NO3","mean_price":0.3863,"compensation":0,"type":"quantile_0.75","estimation_date":"2023-07-25","computation_year":2023,"computation_month":7},{"area":"NO3","mean_price":0.4149,"compensation":0,"type":"quantile_0.9","estimation_date":"2023-07-25","computation_year":2023,"computation_month":7},{"area":"NO3","mean_price":0.431,"compensation":0,"type":"quantile_0.95","estimation_date":"2023-07-25","computation_year":2023,"computation_month":7},{"area":"NO3","mean_price":0.4461,"compensation":0,"type":"quantile_0.975","estimation_date":"2023-07-25","computation_year":2023,"computation_month":7},{"area":"NO3","mean_price":0.4758,"compensation":0,"type":"quantile_0.995","estimation_date":"2023-07-25","computation_year":2023,"computation_month":7},{"area":"NO3","mean_price":0.2969,"compensation":0,"type":"lower_bound","estimation_date":"2023-07-25","computation_year":2023,"computation_month":7},{"area":"NO3","mean_price":0.354,"compensation":0,"type":"current_mean","estimation_date":"2023-07-25","computation_year":2023,"computation_month":7},{"area":"NO4","mean_price":1,"compensation":0,"type":"pos_comp","estimation_date":"2023-07-25","computation_year":2023,"computation_month":7},{"area":"NO4","mean_price":0.2326,"compensation":0,"type":"mean","estimation_date":"2023-07-25","computation_year":2023,"computation_month":7},{"area":"NO4","mean_price":0.2299,"compensation":0,"type":"median","estimation_date":"2023-07-25","computation_year":2023,"computation_month":7},{"area":"NO4","mean_price":0.1861,"compensation":0,"type":"quantile_0.005","estimation_date":"2023-07-25","computation_year":2023,"computation_month":7},{"area":"NO4","mean_price":0.1881,"compensation":0,"type":"quantile_0.025","estimation_date":"2023-07-25","computation_year":2023,"computation_month":7},{"area":"NO4","mean_price":0.1905,"compensation":0,"type":"quantile_0.05","estimation_date":"2023-07-25","computation_year":2023,"computation_month":7},{"area":"NO4","mean_price":0.195,"compensation":0,"type":"quantile_0.1","estimation_date":"2023-07-25","computation_year":2023,"computation_month":7},{"area":"NO4","mean_price":0.2087,"compensation":0,"type":"quantile_0.25","estimation_date":"2023-07-25","computation_year":2023,"computation_month":7},{"area":"NO4","mean_price":0.2525,"compensation":0,"type":"quantile_0.75","estimation_date":"2023-07-25","computation_year":2023,"computation_month":7},{"area":"NO4","mean_price":0.2734,"compensation":0,"type":"quantile_0.9","estimation_date":"2023-07-25","computation_year":2023,"computation_month":7},{"area":"NO4","mean_price":0.2866,"compensation":0,"type":"quantile_0.95","estimation_date":"2023-07-25","computation_year":2023,"computation_month":7},{"area":"NO4","mean_price":0.2966,"compensation":0,"type":"quantile_0.975","estimation_date":"2023-07-25","computation_year":2023,"computation_month":7},{"area":"NO4","mean_price":0.316,"compensation":0,"type":"quantile_0.995","estimation_date":"2023-07-25","computation_year":2023,"computation_month":7},{"area":"NO4","mean_price":0.1861,"compensation":0,"type":"lower_bound","estimation_date":"2023-07-25","computation_year":2023,"computation_month":7},{"area":"NO4","mean_price":0.2218,"compensation":0,"type":"current_mean","estimation_date":"2023-07-25","computation_year":2023,"computation_month":7},{"area":"NO5","mean_price":1,"compensation":0,"type":"pos_comp","estimation_date":"2023-07-25","computation_year":2023,"computation_month":7},{"area":"NO5","mean_price":0.4692,"compensation":0,"type":"mean","estimation_date":"2023-07-25","computation_year":2023,"computation_month":7},{"area":"NO5","mean_price":0.4634,"compensation":0,"type":"median","estimation_date":"2023-07-25","computation_year":2023,"computation_month":7},{"area":"NO5","mean_price":0.4054,"compensation":0,"type":"quantile_0.005","estimation_date":"2023-07-25","computation_year":2023,"computation_month":7},{"area":"NO5","mean_price":0.408,"compensation":0,"type":"quantile_0.025","estimation_date":"2023-07-25","computation_year":2023,"computation_month":7},{"area":"NO5","mean_price":0.4118,"compensation":0,"type":"quantile_0.05","estimation_date":"2023-07-25","computation_year":2023,"computation_month":7},{"area":"NO5","mean_price":0.4183,"compensation":0,"type":"quantile_0.1","estimation_date":"2023-07-25","computation_year":2023,"computation_month":7},{"area":"NO5","mean_price":0.4355,"compensation":0,"type":"quantile_0.25","estimation_date":"2023-07-25","computation_year":2023,"computation_month":7},{"area":"NO5","mean_price":0.4966,"compensation":0,"type":"quantile_0.75","estimation_date":"2023-07-25","computation_year":2023,"computation_month":7},{"area":"NO5","mean_price":0.5286,"compensation":0,"type":"quantile_0.9","estimation_date":"2023-07-25","computation_year":2023,"computation_month":7},{"area":"NO5","mean_price":0.5461,"compensation":0,"type":"quantile_0.95","estimation_date":"2023-07-25","computation_year":2023,"computation_month":7},{"area":"NO5","mean_price":0.5619,"compensation":0,"type":"quantile_0.975","estimation_date":"2023-07-25","computation_year":2023,"computation_month":7},{"area":"NO5","mean_price":0.594,"compensation":0,"type":"quantile_0.995","estimation_date":"2023-07-25","computation_year":2023,"computation_month":7},{"area":"NO5","mean_price":0.4054,"compensation":0,"type":"lower_bound","estimation_date":"2023-07-25","computation_year":2023,"computation_month":7},{"area":"NO5","mean_price":0.4833,"compensation":0,"type":"current_mean","estimation_date":"2023-07-25","computation_year":2023,"computation_month":7}]
